MANIFEST.in
README.md
setup.py
public/__init__.py
public/_iosPerf.py
public/adb.py
public/android_fps.py
public/apm.py
public/apm_pk.py
public/common.py
public/config.json
public/__pycache__/__init__.cpython-313.pyc
public/__pycache__/_iosPerf.cpython-313.pyc
public/__pycache__/adb.cpython-313.pyc
public/__pycache__/android_fps.cpython-313.pyc
public/__pycache__/apm.cpython-313.pyc
public/__pycache__/apm_pk.cpython-313.pyc
public/__pycache__/common.cpython-313.pyc
public/adb/linux/adb
public/adb/linux_arm/adb
public/adb/mac/adb
public/adb/windows/AdbWinApi.dll
public/adb/windows/AdbWinUsbApi.dll
public/adb/windows/adb.exe
public/iosperf/__init__.py
public/iosperf/__main__.py
public/iosperf/_compat.py
public/iosperf/_crash.py
public/iosperf/_device.py
public/iosperf/_hexdump.py
public/iosperf/_imagemounter.py
public/iosperf/_installation.py
public/iosperf/_instruments.py
public/iosperf/_ipautil.py
public/iosperf/_perf.py
public/iosperf/_proto.py
public/iosperf/_relay.py
public/iosperf/_safe_socket.py
public/iosperf/_ssl.py
public/iosperf/_sync.py
public/iosperf/_types.py
public/iosperf/_usbmux.py
public/iosperf/_utils.py
public/iosperf/_version.py
public/iosperf/_wdaproxy.py
public/iosperf/bplist.py
public/iosperf/exceptions.py
public/iosperf/plistlib2.py
public/iosperf/requests_usbmux.py
public/iosperf/struct2.py
public/iosperf/__pycache__/__init__.cpython-313.pyc
public/iosperf/__pycache__/__main__.cpython-313.pyc
public/iosperf/__pycache__/_compat.cpython-313.pyc
public/iosperf/__pycache__/_crash.cpython-313.pyc
public/iosperf/__pycache__/_device.cpython-313.pyc
public/iosperf/__pycache__/_hexdump.cpython-313.pyc
public/iosperf/__pycache__/_imagemounter.cpython-313.pyc
public/iosperf/__pycache__/_installation.cpython-313.pyc
public/iosperf/__pycache__/_instruments.cpython-313.pyc
public/iosperf/__pycache__/_ipautil.cpython-313.pyc
public/iosperf/__pycache__/_perf.cpython-313.pyc
public/iosperf/__pycache__/_proto.cpython-313.pyc
zy_similar.egg-info/PKG-INFO
zy_similar.egg-info/SOURCES.txt
zy_similar.egg-info/dependency_links.txt
zy_similar.egg-info/entry_points.txt
zy_similar.egg-info/requires.txt
zy_similar.egg-info/top_level.txt