Metadata-Version: 2.1
Name: zy-similar
Version: 0.1.0
Summary: A Python package for similarity analysis
Home-page: https://github.com/zhangzhanghua?tab=repositories
Author: Your Name
Author-email: 924179146@qq.com
License: UNKNOWN
Platform: UNKNOWN
Classifier: Programming Language :: Python :: 3
Classifier: License :: OSI Approved :: MIT License
Classifier: Operating System :: OS Independent
Requires-Python: >=3.6
